Metadata-Version: 2.1
Name: rhttp-python
Version: 0.0.3
Summary: RHTTP python interface
Home-page: https://github.com/pedramcode/RHTTP-python
Author: Pedram Dehghanpour
Author-email: dev.dehghanpour@gmail.com
License: MIT
Classifier: Development Status :: 2 - Pre-Alpha
Classifier: Intended Audience :: Developers
Classifier: Intended Audience :: Information Technology
Classifier: License :: OSI Approved :: MIT License
Classifier: Operating System :: POSIX :: Linux
Classifier: Programming Language :: Python :: 3.9
Classifier: Programming Language :: Python :: 3.10
Classifier: Topic :: Internet :: WWW/HTTP
Classifier: Topic :: Internet :: WWW/HTTP :: HTTP Servers
Classifier: Topic :: System :: Networking
License-File: LICENSE
